initkit/__init__.py
initkit/cli.py
initkit/templates/.env.template
initkit/templates/README.md.template
initkit/templates/__init__.py.template
initkit/templates/about.html.template
initkit/templates/base.html.template
initkit/templates/config.py.template
initkit/templates/index.html.template
initkit/templates/models.py.template
initkit/templates/requirements.txt.template
initkit/templates/run.py.template
initkit/templates/style.css.template
initkit/templates/views.py.template
initkit-0.2.0.dist-info/METADATA
initkit-0.2.0.dist-info/WHEEL
initkit-0.2.0.dist-info/entry_points.txt
initkit-0.2.0.dist-info/top_level.txt
initkit-0.2.0.dist-info/RECORD
