Metadata-Version: 2.2
Name: initkit
Version: 0.2.0
Summary: A Flask CLI tool for generating starter templates
Home-page: https://github.com/lyznne/flask-blog-starter.git
Author: lyznne
Author-email: emuthiani26@gmail.com
Project-URL: Bug Reports, https://github.com/lyznne/flask-blog-starter/issues
Project-URL: Source, https://github.com/lyznne/flask-blog-starter
Keywords: flask,cli,template,starter,boilerplate
Classifier: Development Status :: 3 - Alpha
Classifier: Programming Language :: Python :: 3
Classifier: Programming Language :: Python :: 3.7
Classifier: Programming Language :: Python :: 3.8
Classifier: Programming Language :: Python :: 3.9
Classifier: Programming Language :: Python :: 3.12
Classifier: License :: OSI Approved :: MIT License
Classifier: Operating System :: OS Independent
Classifier: Intended Audience :: Developers
Classifier: Topic :: Software Development :: Code Generators
Classifier: Topic :: Software Development :: Libraries :: Python Modules
Requires-Python: >=3.7
Requires-Dist: Flask>=2.3.2
Requires-Dist: click>=8.1.3
Requires-Dist: python-dotenv>=0.19.0
Dynamic: author
Dynamic: author-email
Dynamic: classifier
Dynamic: description
Dynamic: description-content-type
Dynamic: home-page
Dynamic: keywords
Dynamic: project-url
Dynamic: requires-dist
Dynamic: requires-python
Dynamic: summary
